Android101Labs/README.md
Android101Labs/__init__.py
Android101Labs/__main__.py
Android101Labs/file.epub
Android101Labs/index.html
Android101Labs/css/__init__.py
Android101Labs/css/annotations.css
Android101Labs/css/main.css
Android101Labs/css/normalize.css
Android101Labs/css/popup.css
Android101Labs/font/__init__.py
Android101Labs/font/fontello.eot
Android101Labs/font/fontello.svg
Android101Labs/font/fontello.ttf
Android101Labs/font/fontello.woff
Android101Labs/img/__init__.py
Android101Labs/img/annotator-glyph-sprite.png
Android101Labs/img/annotator-icon-sprite.png
Android101Labs/img/apple-touch-icon.png
Android101Labs/img/cancelfullscreen.png
Android101Labs/img/close.png
Android101Labs/img/fullscreen.png
Android101Labs/img/loader.gif
Android101Labs/img/menu-icon.png
Android101Labs/img/save.png
Android101Labs/img/saved.png
Android101Labs/img/settings-s.png
Android101Labs/img/settings.png
Android101Labs/img/star.png
Android101Labs/js/__init__.py
Android101Labs/js/epub.js
Android101Labs/js/epub.min.js
Android101Labs/js/epub.min.map
Android101Labs/js/hooks.min.js
Android101Labs/js/hooks.min.map
Android101Labs/js/reader.js
Android101Labs/js/reader.js.map
Android101Labs/js/reader.min.js
Android101Labs/js/reader.min.map
Android101Labs/js/hooks/__init__.py
Android101Labs/js/hooks/extensions/__init__.py
Android101Labs/js/hooks/extensions/highlight.js
Android101Labs/js/libs/__init__.py
Android101Labs/js/libs/jquery.min.js
Android101Labs/js/libs/localforage.min.js
Android101Labs/js/libs/screenfull.js
Android101Labs/js/libs/screenfull.min.js
Android101Labs/js/libs/zip.min.js
Android101Labs/js/plugins/__init__.py
Android101Labs/js/plugins/hypothesis.js
Android101Labs/js/plugins/search.js
android_101_labs-2024.3.3.0.dist-info/METADATA
android_101_labs-2024.3.3.0.dist-info/WHEEL
android_101_labs-2024.3.3.0.dist-info/entry_points.txt
android_101_labs-2024.3.3.0.dist-info/top_level.txt
android_101_labs-2024.3.3.0.dist-info/RECORD
